{
    "fluentMethods": true,
    "relationships": [],
    "fields": [
        {
            "fieldName": "name",
            "fieldType": "String",
            "fieldValidateRules": [
                "required"
            ]
        },
        {
            "fieldName": "difficulty",
            "fieldType": "OpponentDifficulty",
            "fieldValues": "CHILDISH,EASY,NORMAL,HARD,NIGHTMARE",
            "fieldValidateRules": [
                "required"
            ]
        }
    ],
    "changelogDate": "20180222203943",
    "javadoc": "Opponent used to battle against a user.\nname: the opponent name, Ex: Glados, Wheatley\ndifficulty: the difficulty the user has to face",
    "entityTableName": "opponent",
    "dto": "no",
    "pagination": "no",
    "service": "serviceImpl",
    "jpaMetamodelFiltering": false
}